{
  "date": "",
  "reported_companies": [],
  "alpha_vantage_calls_today": 0,
  "runs": {
    "10:30": {"companies": [], "status": "pending"},
    "12:30": {"companies": [], "status": "pending"},
    "14:30": {"companies": [], "status": "pending"},
    "16:10": {"companies": [], "status": "pending"}
  },
  "failed_tickers": [],
  "api_failures": {},
  "sector_scores_today": {},
  "breadth_score_today": null,
  "sector_breadth_ma_today": {},
  "unusual_volume_flags": [],
  "event_scores_today": {},
  "indices_today": {}
}
