{
  "ticker": "GM",
  "current_price": 76.42,
  "market_cap": 71289257984,
  "avg_volume": 8241759,
  "beta": 1.345,
  "revenue_ttm": 185019000000.0,
  "revenue_prev_year": 187442000000.0,
  "net_income_ttm": 2697000000.0,
  "eps_ttm": 3.27,
  "eps_quarterly": [
    1.37,
    1.94,
    3.4,
    2.71
  ],
  "profit_margin": 1.4579999,
  "debt_to_equity": 2.08299,
  "operating_cash_flow": 26866999296,
  "pe_ratio": 23.37003,
  "earnings_date": "2026-04-28",
  "industry": "Auto Manufacturers",
  "sector": "Consumer Cyclical",
  "data_source": "yfinance",
  "cross_validated": false,
  "price_history": [
    78.52,
    77.58,
    77.09,
    78.41,
    76.02,
    75.21,
    74.69,
    74.93,
    74.79,
    73.45,
    72.39,
    72.95,
    74.04,
    73.53,
    73.79,
    72.81,
    75.72,
    76.57,
    76.61,
    75.6,
    72.98,
    72.76,
    74.5,
    75.04,
    72.54,
    73.43,
    72.76,
    76.74,
    76.73,
    76.42
  ],
  "_cached_at": "2026-04-10T20:55:41.736596+00:00"
}