{
  "ticker": "GM",
  "current_price": 79.225,
  "market_cap": 71616856064,
  "avg_volume": 7886345,
  "beta": 1.345,
  "revenue_ttm": 185019000000.0,
  "revenue_prev_year": 187442000000.0,
  "net_income_ttm": 2697000000.0,
  "eps_ttm": 3.27,
  "eps_quarterly": [
    1.37,
    1.94,
    3.4,
    2.71
  ],
  "profit_margin": 1.4579999,
  "debt_to_equity": 2.08299,
  "operating_cash_flow": 26866999296,
  "pe_ratio": 24.227829,
  "earnings_date": "2026-04-28",
  "industry": "Auto Manufacturers",
  "sector": "Consumer Cyclical",
  "data_source": "yfinance",
  "cross_validated": false,
  "price_history": [
    74.79,
    73.45,
    72.39,
    72.95,
    74.04,
    73.53,
    73.79,
    72.81,
    75.72,
    76.57,
    76.61,
    75.6,
    72.98,
    72.76,
    74.5,
    75.04,
    72.54,
    73.43,
    72.76,
    76.74,
    76.73,
    76.42,
    76.83,
    79.46,
    77.78,
    78.05,
    81.32,
    80.54,
    79.05,
    79.22
  ],
  "_cached_at": "2026-04-22T15:02:39.990775+00:00"
}