{
  "ticker": "LIN",
  "current_price": 494.57,
  "market_cap": 229180850176,
  "avg_volume": 2689306,
  "beta": 0.797,
  "revenue_ttm": 33986000000.0,
  "revenue_prev_year": 33005000000.0,
  "net_income_ttm": 6898000000.0,
  "eps_ttm": 14.62,
  "eps_quarterly": [
    3.28,
    4.11,
    3.75,
    3.53,
    3.24
  ],
  "profit_margin": 20.297001,
  "debt_to_equity": 0.7062999999999999,
  "operating_cash_flow": 10350000128,
  "pe_ratio": 33.82832,
  "earnings_date": "2026-04-30",
  "industry": "Specialty Chemicals",
  "sector": "Basic Materials",
  "data_source": "yfinance",
  "cross_validated": false,
  "_cached_at": "2026-03-26T14:52:15.273381+00:00"
}