{
  "ticker": "MRVL",
  "current_price": 133.83,
  "market_cap": 117028749312,
  "avg_volume": 19857300,
  "beta": 1.822,
  "revenue_ttm": 8194600000.0,
  "revenue_prev_year": 5767300000.0,
  "net_income_ttm": 2670100000.0,
  "eps_ttm": 3.07,
  "eps_quarterly": [
    0.47,
    2.22,
    0.23,
    0.21,
    0.23
  ],
  "profit_margin": 32.584,
  "debt_to_equity": 0.33479,
  "operating_cash_flow": 1750499968,
  "pe_ratio": 43.592834,
  "earnings_date": "2026-05-28",
  "industry": "Semiconductors",
  "sector": "Technology",
  "data_source": "yfinance",
  "cross_validated": false,
  "price_history": [
    77.47,
    78.05,
    75.64,
    89.53,
    92.6,
    93.25,
    90.39,
    87.63,
    87.82,
    91.53,
    90.74,
    87.58,
    89.49,
    87.87,
    90.11,
    92.31,
    98.4,
    97.63,
    94.83,
    87.77,
    99.0,
    106.66,
    107.06,
    109.46,
    109.33,
    114.39,
    119.87,
    128.49,
    131.3,
    133.83
  ],
  "_cached_at": "2026-04-14T21:08:33.171619+00:00"
}