{
  "ticker": "NUE",
  "current_price": 166.442,
  "market_cap": 38091694080,
  "avg_volume": 1730098,
  "beta": 1.768,
  "revenue_ttm": 32494000000.0,
  "revenue_prev_year": 30734000000.0,
  "net_income_ttm": 1744000000.0,
  "eps_ttm": 7.52,
  "eps_quarterly": [
    1.64,
    2.63,
    2.6,
    0.67,
    1.22
  ],
  "profit_margin": 5.367,
  "debt_to_equity": 0.32765,
  "operating_cash_flow": 3233999872,
  "pe_ratio": 22.133245,
  "earnings_date": "2026-04-27",
  "industry": "Steel",
  "sector": "Basic Materials",
  "data_source": "yfinance",
  "cross_validated": false,
  "_cached_at": "2026-03-26T14:52:23.029212+00:00"
}