{
  "ticker": "RRC",
  "current_price": 41.98,
  "market_cap": 9891422208,
  "avg_volume": 3512340,
  "beta": 0.46,
  "revenue_ttm": 2988164000.0,
  "revenue_prev_year": 2346898000.0,
  "net_income_ttm": 658024000.0,
  "eps_ttm": 3.78,
  "eps_quarterly": [
    1.45,
    0.76,
    0.61,
    0.99,
    0.4
  ],
  "profit_margin": 28.118,
  "debt_to_equity": 0.21275,
  "operating_cash_flow": 1460376960,
  "pe_ratio": 11.10582,
  "earnings_date": "2026-04-21",
  "industry": "Oil & Gas E&P",
  "sector": "Energy",
  "data_source": "yfinance",
  "cross_validated": false,
  "price_history": [
    43.67,
    44.25,
    43.33,
    42.93,
    42.84,
    41.9,
    40.69,
    41.22,
    42.27,
    41.71,
    41.14,
    41.67,
    43.25,
    42.64,
    42.36,
    42.22,
    42.94,
    43.26,
    43.5,
    42.63,
    43.0,
    43.04,
    41.17,
    40.86,
    40.52,
    40.97,
    40.9,
    41.26,
    41.49,
    41.98
  ],
  "_cached_at": "2026-05-15T15:52:31.361040+00:00"
}