{
  "ticker": "ZION",
  "current_price": 57.65,
  "market_cap": 8525791232,
  "avg_volume": 1904141,
  "beta": 0.822,
  "revenue_ttm": 3385000000.0,
  "revenue_prev_year": 3130000000.0,
  "net_income_ttm": 899000000.0,
  "eps_ttm": 6.01,
  "eps_quarterly": [
    1.76,
    1.48,
    1.63,
    1.13,
    1.34
  ],
  "profit_margin": 27.136,
  "debt_to_equity": null,
  "operating_cash_flow": 1073000000,
  "pe_ratio": 9.592346,
  "earnings_date": "2026-04-20",
  "industry": "Banks - Regional",
  "sector": "Financial Services",
  "data_source": "yfinance",
  "cross_validated": false,
  "price_history": [
    62.04,
    61.48,
    62.5,
    59.3,
    59.2,
    60.4,
    61.65,
    57.28,
    58.14,
    57.65,
    58.22,
    57.48,
    55.74,
    55.78,
    55.42,
    54.85,
    54.24,
    53.1,
    53.54,
    54.02,
    53.62,
    54.28,
    54.05,
    55.05,
    56.22,
    57.2,
    57.25,
    55.4,
    55.59,
    57.65
  ],
  "_cached_at": "2026-03-31T18:38:51.910834+00:00"
}